tests/__init__.py
tests/test_tasks.py
tests/test_views.py
udata_transport/__init__.py
udata_transport/settings.py
udata_transport/tasks.py
udata_transport/views.py
udata_transport/templates/dataset-transport.html
udata_transport-1.0.1.dist-info/METADATA
udata_transport-1.0.1.dist-info/WHEEL
udata_transport-1.0.1.dist-info/entry_points.txt
udata_transport-1.0.1.dist-info/top_level.txt
udata_transport-1.0.1.dist-info/RECORD
