Metadata-Version: 2.1
Name: udata-transport
Version: 1.0.1
Summary: Transport.data.gouv.fr mapping to Udata
Home-page: https://github.com/opendatateam/udata-transport
Author: Opendata Team
Author-email: opendatateam@data.gouv.fr
License: GNU AGPLv3+
Keywords: udata transport
Classifier: Development Status :: 5 - Production/Stable
Classifier: Programming Language :: Python
Classifier: Environment :: Web Environment
Classifier: Operating System :: OS Independent
Classifier: Intended Audience :: Developers
Classifier: Topic :: System :: Software Distribution
Classifier: Programming Language :: Python
Classifier: Programming Language :: Python :: 3
Classifier: Programming Language :: Python :: 3.7
Classifier: Topic :: Software Development :: Libraries :: Python Modules
Classifier: License :: OSI Approved :: GNU Affero General Public License v3 or later (AGPLv3+)
Requires-Python: >=3.7
Requires-Dist: udata >=3.2.0
Requires-Dist: udata-front >=1.0.0
Provides-Extra: test
Requires-Dist: pytest ==7.3.1 ; extra == 'test'
Requires-Dist: pytest-flask ==1.2.0 ; extra == 'test'
Requires-Dist: pytest-sugar ==0.9.7 ; extra == 'test'
Requires-Dist: requests-mock ==1.10.0 ; extra == 'test'
Requires-Dist: mock ==5.0.1 ; extra == 'test'
Requires-Dist: pytest-mock ==3.10.0 ; extra == 'test'
